Workbook

Sheet Resumo
A1: PROGRAMA DE CASHBACK — LOJAS LURD'S
A4: Simulador de Tiers + Projeção Financeira
A6: ESTRUTURA DA PLANILHA
A8: • Tiers | B8: Configuração dos 4 níveis (Bronze, Prata, Ouro, Diamante) com critérios e benefícios
A9: • Parametros | B9: Parâmetros globais: validade, resgate mínimo, bônus aniversário, etc.
A10: • Simulador Cliente | B10: Simule o cashback gerado por uma cliente individual — varie tier, ticket, frequência
A11: • Projecao Anual | B11: Projeção financeira do programa em 3 cenários (conservador / realista / otimista)
A12: • Distribuicao Tiers | B12: Modelo de distribuição esperada da base por tier após maturação
A13: • Cronograma | B13: Roadmap dos próximos 90 dias de implementação
A16: LEGENDA DE CORES
A18: Azul | B18: Célula de INPUT — você pode alterar livremente
A19: Preto | B19: Célula CALCULADA — fórmula automática, não altere
A20: Amarelo | B20: Premissa-chave do modelo, revise antes de usar

Sheet Tiers
A1: CONFIGURAÇÃO DOS TIERS DE CASHBACK
A3: Tier | B3: Critério (gasto 12m) | C3: % Cashback | D3: Validade (dias) | E3: Frete grátis acima de | F3: Frete grátis sempre | G3: Brinde aniversário | H3: Acesso antecipado / VIP
A4: Bronze | B4: 0 | C4: 0.03 | D4: 60 | E4: — | F4: Não | G4: Não | H4: Não
A5: Prata | B5: 1500 | C5: 0.05 | D5: 90 | E5: 199 | F5: Não | G5: Sim | H5: Não
A6: Ouro | B6: 4000 | C6: 0.07 | D6: 120 | E6: — | F6: Sim | G6: Sim | H6: Não
A7: Diamante | B7: 10000 | C7: 0.1 | D7: 180 | E7: — | F7: Sim | G7: Sim | H7: Sim (VIP)
A10: Notas:
A11: • Cliente sobe de tier ASSIM QUE atinge a meta de 12m. Avaliação automática diária.
A12: • Cliente permanece no tier por 12 meses sem comprar. Após isso, recalcula.
A13: • Diamante recebe convite por chamada direta — sinalização exclusiva.

Sheet Parametros
A1: PARÂMETROS GLOBAIS DO PROGRAMA
A3: Parâmetro | B3: Valor | C3: Unidade | D3: Descrição / Lógica
A4: Resgate mínimo | B4: 20 | C4: R$ | D4: Saldo mínimo para começar a usar
A5: Uso máximo por compra | B5: 0.3 | C5: % | D5: Cliente pode pagar até X% da compra em cashback
A6: Carência crédito | B6: 7 | C6: dias | D6: Dias entre venda e crédito (devolução)
A7: Aviso suave expiração | B7: 30 | C7: dias antes | D7: Primeiro WhatsApp avisando
A8: Aviso urgente expiração | B8: 7 | C8: dias antes | D8: WhatsApp urgência
A9: Bônus boas-vindas | B9: 20 | C9: R$ | D9: Crédito ao completar cadastro + LGPD
A10: Bônus indicação (indicadora) | B10: 30 | C10: R$ | D10: Para quem indica, após 1ª compra da indicada
A11: Bônus indicação (indicada) | B11: 30 | C11: R$ | D11: Para quem foi indicada, após 1ª compra dela
A12: Bônus reativação | B12: 25 | C12: R$ | D12: Cliente sumida 90+ dias (campanha)
A13: Multiplicador aniversário | B13: 2 | C13: x | D13: Cashback DOBRA no mês de aniversário
A14: Multiplicador dias fracos (qua/qui) | B14: 1.5 | C14: x | D14: Cashback 50% maior em qua/qui
A15: Multiplicador 1ª compra alta | B15: 2 | C15: x | D15: Dobra se 1ª compra ≥ R$ 500
... A17: Inatividade para reativação | B17: 90 | C17: dias | D17: Dias sem comprar = inativa

Sheet Simulador Cliente
A1: SIMULADOR DE CASHBACK POR CLIENTE
A3: INPUTS (altere os valores em azul)
A4: Tier da cliente | B4: Prata | C4: Bronze / Prata / Ouro / Diamante
A5: Ticket médio (R$) | B5: 280 | C5: Valor médio gasto por compra
A6: Compras por ano | B6: 6 | C6: Frequência anual
A7: É mês de aniversário? | B7: Não | C7: Sim aplica multiplicador 2x
A8: É compra em qua/qui? | B8: Não | C8: Sim aplica multiplicador 1.5x
A11: CÁLCULO
A12: % Cashback do tier | B12: =VLOOKUP(B4,Tiers!A4:C7,3,FALSE()) -> 0.05
A13: Multiplicador aniversário | B13: =IF(B7="Sim",Parametros!B13,1) -> 1
A14: Multiplicador qua/qui | B14: =IF(B8="Sim",Parametros!B14,1) -> 1
A15: % efetivo aplicado | B15: =B12*B13*B14 -> 0.05
A16: Cashback por compra (R$) | B16: =B5*B15 -> 14
A17: Cashback anual gerado (R$) | B17: =B16*B6 -> 84
A18: Faturamento da cliente / ano (R$) | B18: =B5*B6 -> 1680
A19: Custo do cashback s/ faturamento | B19: =B17/B18 -> 0.05
A22: COMPARATIVO ENTRE TIERS (mesmo perfil de compra)
A23: Tier | B23: % Cashback | C23: Cashback/ano | D23: Fat./ano | E23: Custo %
A24: Bronze | B24: =VLOOKUP(A24,Tiers!A4:C7,3,FALSE()) -> 0.03 | C24: =$B$5*$B$6*B24 -> 50.4 | D24: =$B$5*$B$6 -> 1680 | E24: =C24/D24 -> 0.03
A25: Prata | B25: =VLOOKUP(A25,Tiers!A4:C7,3,FALSE()) -> 0.05 | C25: =$B$5*$B$6*B25 -> 84 | D25: =$B$5*$B$6 -> 1680 | E25: =C25/D25 -> 0.05
A26: Ouro | B26: =VLOOKUP(A26,Tiers!A4:C7,3,FALSE()) -> 0.07 | C26: =$B$5*$B$6*B26 -> 117.6 | D26: =$B$5*$B$6 -> 1680 | E26: =C26/D26 -> 0.07
A27: Diamante | B27: =VLOOKUP(A27,Tiers!A4:C7,3,FALSE()) -> 0.1 | C27: =$B$5*$B$6*B27 -> 168 | D27: =$B$5*$B$6 -> 1680 | E27: =C27/D27 -> 0.1

Sheet Projecao Anual
A1: PROJEÇÃO FINANCEIRA — 12 MESES
A3: PREMISSAS BASE (altere para simular)
A4: Base atual de clientes ativos | B4: 7695 | C4: Total cadastros Giga
A5: % clientes elegíveis (com celular) | B5: 0.3 | C5: Quem dá pra impactar via WhatsApp
A6: % adesão ao cashback | B6: 0.5 | C6: Dos elegíveis, quantos % vão usar
A7: Ticket médio (R$) | B7: 280 | C7: Valor médio por compra
A8: Compras médias / ano por cliente | B8: 4 | C8: Frequência média
A9: % adicional de compra por causa do cashback | B9: 0.15 | C9: Lift de frequência esperado
A10: % cashback médio efetivo | B10: 0.045 | C10: Mix entre tiers (média ponderada)
A11: % resgate efetivo | B11: 0.7 | C11: % do cashback gerado que é resgatado
A14: CÁLCULO
A15: Clientes elegíveis | B15: =B4*B5 -> 2308.5
A16: Clientes aderindo ao programa | B16: =B15*B6 -> 1154.25
A17: Compras/ano SEM cashback (todos) | B17: =B16*B8 -> 4617
A18: Compras/ano COM cashback (aderentes) | B18: =B16*B8*(1+B9) -> 5309.55
A19: Compras incrementais geradas/ano | B19: =B18-B17 -> 692.55
A20: Faturamento SEM cashback (R$) | B20: =B17*B7 -> 1292760
A21: Faturamento COM cashback (R$) | B21: =B18*B7 -> 1486674
A22: Faturamento INCREMENTAL (R$) | B22: =B21-B20 -> 193914
A23: Cashback gerado (R$) | B23: =B21*B10 -> 66900.33
A24: Cashback efetivamente resgatado (R$) | B24: =B23*B11 -> 46830.231
A25: CUSTO REAL do programa (R$) | B25: =B24 -> 46830.231
A26: ROI do programa (Faturamento incremental / custo) | B26: =B22/B25 -> 4.1407867
A27: ROI bruto (Faturamento total novo / custo) | B27: =B21/B25 -> 31.746032
A29: CENÁRIOS (alteração apenas das premissas-chave)
A30: Cenário | B30: Adesão | C30: Lift | D30: Resgate | E30: Custo (R$) | F30: Faturamento incremental
A31: Conservador | B31: 0.3 | C31: 0.08 | D31: 0.6 | E31: =$B$4*$B$5*B31*$B$8*(1+C31)*$B$7*$B$10*D31 -> 22618.129 | F31: =$B$4*$B$5*B31*$B$8*C31*$B$7 -> 62052.48
A32: Realista | B32: 0.5 | C32: 0.15 | D32: 0.7 | E32: =$B$4*$B$5*B32*$B$8*(1+C32)*$B$7*$B$10*D32 -> 46830.231 | F32: =$B$4*$B$5*B32*$B$8*C32*$B$7 -> 193914
A33: Otimista | B33: 0.7 | C33: 0.25 | D33: 0.8 | E33: =$B$4*$B$5*B33*$B$8*(1+C33)*$B$7*$B$10*D33 -> 81443.88 | F33: =$B$4*$B$5*B33*$B$8*C33*$B$7 -> 452466

Sheet Distribuicao Tiers
A1: DISTRIBUIÇÃO ESPERADA DA BASE POR TIER (após 12m)
A3: Pirâmide típica de programa de fidelidade plus size (benchmark mercado)
A5: Tier | B5: % da base | C5: Qtd clientes (estimada) | D5: Faturamento médio/ano | E5: Faturamento total/ano
A6: Bronze | B6: 0.65 | C6: =ROUND($B$11*B6,0) -> 750 | D6: 800 | E6: =C6*D6 -> 600000
A7: Prata | B7: 0.25 | C7: =ROUND($B$11*B7,0) -> 289 | D7: 2200 | E7: =C7*D7 -> 635800
A8: Ouro | B8: 0.08 | C8: =ROUND($B$11*B8,0) -> 92 | D8: 5500 | E8: =C8*D8 -> 506000
A9: Diamante | B9: 0.02 | C9: =ROUND($B$11*B9,0) -> 23 | D9: 14000 | E9: =C9*D9 -> 322000
A10: TOTAL | B10: =SUM(B6:B9) -> 1 | C10: =SUM(C6:C9) -> 1154 | E10: =SUM(E6:E9) -> 2063800
A11: Base total aderente (input): | B11: 1154

Sheet Cronograma
A1: CRONOGRAMA DE IMPLEMENTAÇÃO — 90 DIAS
A3: Semana | B3: Frente | C3: Ação | D3: Responsável | E3: Status
A4: Sem 1 | B4: TI/Banco | C4: Provisionar PostgreSQL (Supabase ou RDS) | D4: TI | E4: A fazer
A5: Sem 1 | B5: TI/Banco | C5: Rodar 01_schema_crm.sql (criar estrutura) | D5: TI | E5: A fazer
A6: Sem 1 | B6: Operação | C6: Definir termo LGPD oficial (jurídico) | D6: Jurídico | E6: A fazer
A7: Sem 2 | B7: TI/Banco | C7: Exportar clientes do Giga + rodar 02_migracao_inicial | D7: TI | E7: A fazer
A8: Sem 2 | B8: TI/Banco | C8: Rodar 04_regras_cashback.sql (regras de negócio) | D8: TI | E8: A fazer
A9: Sem 2 | B9: Marketing | C9: Criar arte de cartão fidelidade físico | D9: Marketing | E9: A fazer
A10: Sem 3 | B10: Operação | C10: Treinar vendedoras: novo fluxo PDV + script captura | D10: Gerência | E10: A fazer
A11: Sem 3 | B11: Marketing | C11: Preparar templates WhatsApp (boas-vindas, saldo, expiração) | D11: Marketing | E11: A fazer
A12: Sem 4 | B12: Operação | C12: PILOTO em 1 loja (Itanhaém) — coleta cadastro + testa cashback | D12: Loja piloto | E12: A fazer
A13: Sem 4 | B13: Operação | C13: Coleta diária de feedback das vendedoras | D13: Gerência | E13: A fazer
A14: Sem 5-6 | B14: Operação | C14: Ajustes finos no fluxo baseado no piloto | D14: Todos | E14: A fazer
... A21: Sem 11-12 | B21: Marketing | C21: Ajustar régua de comunicação baseado em dados | D21: Marketing | E21: A fazer
